{"nodes": [{"id": "agent_workflows_instinct_export", "label": "Instinct Export Workflow", "file_type": "document", "source_file": ".agent/workflows/instinct-export.md", "source_location": null, "source_url": null, "captured_at": null, "author": null, "contributor": null}], "edges": [{"source": "agent_workflows_instinct_export", "target": "concept_instinct_system", "relation": "references", "confidence": "EXTRACTED", "confidence_score": 1.0, "source_file": ".agent/workflows/instinct-export.md", "source_location": null, "weight": 1.0}], "hyperedges": []}